Metadata-Version: 1.0
Name: squareonly
Version: 0.0.1
Summary: This is a simple module which can help you to find the Area of 2D shapes
Home-page: UNKNOWN
Author: Sudhanshu Yadav
Author-email: sudhanshuy17@email.com
License: PYPI
Platform: UNKNOWN
